[
    {
        "Type of Cases": "NSP",
        "I Qtr 2024": "239",
        "II Qtr 2024": "272",
        "III Qtr 2024": "195",
        "IV Qtr 2024": "185",
        "Total 2024": "891"
    },
    {
        "Type of Cases": "NSN",
        "I Qtr 2024": "187",
        "II Qtr 2024": "223",
        "III Qtr 2024": "170",
        "IV Qtr 2024": "155",
        "Total 2024": "735"
    },
    {
        "Type of Cases": "New EP",
        "I Qtr 2024": "424",
        "II Qtr 2024": "509",
        "III Qtr 2024": "432",
        "IV Qtr 2024": "370",
        "Total 2024": "1735"
    },
    {
        "Type of Cases": "Others",
        "I Qtr 2024": "0",
        "II Qtr 2024": "0",
        "III Qtr 2024": "0",
        "IV Qtr 2024": "0",
        "Total 2024": "0"
    },
    {
        "Type of Cases": "New Cases Total",
        "I Qtr 2024": "850",
        "II Qtr 2024": "1004",
        "III Qtr 2024": "797",
        "IV Qtr 2024": "710",
        "Total 2024": "3361"
    },
    {
        "Type of Cases": "Recurrent TB",
        "I Qtr 2024": "53",
        "II Qtr 2024": "41",
        "III Qtr 2024": "54",
        "IV Qtr 2024": "46",
        "Total 2024": "194"
    },
    {
        "Type of Cases": "Treatment After Failure",
        "I Qtr 2024": "0",
        "II Qtr 2024": "2",
        "III Qtr 2024": "0",
        "IV Qtr 2024": "0",
        "Total 2024": "2"
    },
    {
        "Type of Cases": "Treatment After Loss to Follow-up",
        "I Qtr 2024": "9",
        "II Qtr 2024": "1",
        "III Qtr 2024": "2",
        "IV Qtr 2024": "8",
        "Total 2024": "20"
    },
    {
        "Type of Cases": "Other Previously Treated Patients",
        "I Qtr 2024": "70",
        "II Qtr 2024": "64",
        "III Qtr 2024": "63",
        "IV Qtr 2024": "68",
        "Total 2024": "265"
    },
    {
        "Type of Cases": "Retreatment cases Total",
        "I Qtr 2024": "132",
        "II Qtr 2024": "108",
        "III Qtr 2024": "119",
        "IV Qtr 2024": "122",
        "Total 2024": "481"
    },
    {
        "Type of Cases": "Grand Total",
        "I Qtr 2024": "982",
        "II Qtr 2024": "1112",
        "III Qtr 2024": "916",
        "IV Qtr 2024": "832",
        "Total 2024": "3842"
    },
    {
        "Type of Cases": "Total NSP conversion Cases",
        "I Qtr 2024": "180",
        "II Qtr 2024": "239",
        "III Qtr 2024": "272",
        "IV Qtr 2024": "195",
        "Total 2024": "886"
    },
    {
        "Type of Cases": "NSP Negative",
        "I Qtr 2024": "155",
        "II Qtr 2024": "189",
        "III Qtr 2024": "224",
        "IV Qtr 2024": "159",
        "Total 2024": "727"
    },
    {
        "Type of Cases": "NSP Positive",
        "I Qtr 2024": "6",
        "II Qtr 2024": "19",
        "III Qtr 2024": "19",
        "IV Qtr 2024": "14",
        "Total 2024": "58"
    },
    {
        "Type of Cases": "NSP Not done",
        "I Qtr 2024": "19",
        "II Qtr 2024": "31",
        "III Qtr 2024": "29",
        "IV Qtr 2024": "22",
        "Total 2024": "101"
    },
    {
        "Type of Cases": "NSP Conversion rate",
        "I Qtr 2024": "86",
        "II Qtr 2024": "79",
        "III Qtr 2024": "82",
        "IV Qtr 2024": "82",
        "Total 2024": "82"
    },
    {
        "Type of Cases": "Total RT conversion Cases",
        "I Qtr 2024": "38",
        "II Qtr 2024": "62",
        "III Qtr 2024": "44",
        "IV Qtr 2024": "56",
        "Total 2024": "200"
    },
    {
        "Type of Cases": "RT Negative",
        "I Qtr 2024": "30",
        "II Qtr 2024": "54",
        "III Qtr 2024": "41",
        "IV Qtr 2024": "46",
        "Total 2024": "171"
    },
    {
        "Type of Cases": "RT Positive",
        "I Qtr 2024": "3",
        "II Qtr 2024": "4",
        "III Qtr 2024": "2",
        "IV Qtr 2024": "4",
        "Total 2024": "13"
    },
    {
        "Type of Cases": "RT not done",
        "I Qtr 2024": "5",
        "II Qtr 2024": "4",
        "III Qtr 2024": "1",
        "IV Qtr 2024": "6",
        "Total 2024": "16"
    },
    {
        "Type of Cases": "RT Conversion rate",
        "I Qtr 2024": "79",
        "II Qtr 2024": "87",
        "III Qtr 2024": "93",
        "IV Qtr 2024": "82",
        "Total 2024": "86"
    }
]