[
    {
        "Type of cases ": "NSP Cured",
        "I Qtr-2023": "198",
        "II Qtr-2023": "212",
        "III Qtr-2023": "214",
        "IV Qtr-2023": "141",
        "Total 2023": "765",
        "%": "85"
    },
    {
        "Type of cases ": "NSP Treatment completed",
        "I Qtr-2023": "0",
        "II Qtr-2023": "0",
        "III Qtr-2023": "0",
        "IV Qtr-2023": "3",
        "Total 2023": "3",
        "%": "0"
    },
    {
        "Type of cases ": "NSP Died",
        "I Qtr-2023": "7",
        "II Qtr-2023": "9",
        "III Qtr-2023": "8",
        "IV Qtr-2023": "7",
        "Total 2023": "31",
        "%": "3"
    },
    {
        "Type of cases ": "NSP Failure",
        "I Qtr-2023": "3",
        "II Qtr-2023": "1",
        "III Qtr-2023": "1",
        "IV Qtr-2023": "4",
        "Total 2023": "9",
        "%": "1"
    },
    {
        "Type of cases ": "NSP Lost to Follow-up",
        "I Qtr-2023": "8",
        "II Qtr-2023": "7",
        "III Qtr-2023": "7",
        "IV Qtr-2023": "7",
        "Total 2023": "29",
        "%": "3"
    },
    {
        "Type of cases ": "NSP Not Evaluated",
        "I Qtr-2023": "0",
        "II Qtr-2023": "0",
        "III Qtr-2023": "1",
        "IV Qtr-2023": "0",
        "Total 2023": "1",
        "%": "0.11"
    },
    {
        "Type of cases ": "NSP Treatment Regimen Changed",
        "I Qtr-2023": "22",
        "II Qtr-2023": "20",
        "III Qtr-2023": "12",
        "IV Qtr-2023": "9",
        "Total 2023": "63",
        "%": "6.99"
    },
    {
        "Type of cases ": "NSP Total",
        "I Qtr-2023": "238",
        "II Qtr-2023": "249",
        "III Qtr-2023": "243",
        "IV Qtr-2023": "171",
        "Total 2023": "901",
        "%": ""
    },
    {
        "Type of cases ": "NSN/NEP Cured",
        "I Qtr-2023": "",
        "II Qtr-2023": "",
        "III Qtr-2023": "",
        "IV Qtr-2023": "",
        "Total 2023": "",
        "%": ""
    },
    {
        "Type of cases ": "NSN/NEP Treatment completed",
        "I Qtr-2023": "496",
        "II Qtr-2023": "597",
        "III Qtr-2023": "525",
        "IV Qtr-2023": "421",
        "Total 2023": "2039",
        "%": "97"
    },
    {
        "Type of cases ": "NSN/NEP Died",
        "I Qtr-2023": "10",
        "II Qtr-2023": "6",
        "III Qtr-2023": "9",
        "IV Qtr-2023": "11",
        "Total 2023": "36",
        "%": "2"
    },
    {
        "Type of cases ": "NSN/NEP Failure",
        "I Qtr-2023": "1",
        "II Qtr-2023": "0",
        "III Qtr-2023": "0",
        "IV Qtr-2023": "2",
        "Total 2023": "3",
        "%": "0"
    },
    {
        "Type of cases ": "NSN/NEP Lost to Follow-up",
        "I Qtr-2023": "8",
        "II Qtr-2023": "4",
        "III Qtr-2023": "6",
        "IV Qtr-2023": "4",
        "Total 2023": "22",
        "%": "1"
    },
    {
        "Type of cases ": "NSN/NEP Not Evaluated",
        "I Qtr-2023": "2",
        "II Qtr-2023": "1",
        "III Qtr-2023": "0",
        "IV Qtr-2023": "0",
        "Total 2023": "3",
        "%": "0.14"
    },
    {
        "Type of cases ": "NSN/NEP Treatment Regimen Changed",
        "I Qtr-2023": "2",
        "II Qtr-2023": "0",
        "III Qtr-2023": "1",
        "IV Qtr-2023": "2",
        "Total 2023": "5",
        "%": "0.24"
    },
    {
        "Type of cases ": "NSN/NEP Total",
        "I Qtr-2023": "519",
        "II Qtr-2023": "608",
        "III Qtr-2023": "541",
        "IV Qtr-2023": "440",
        "Total 2023": "2108",
        "%": ""
    },
    {
        "Type of cases ": "RT +ve Cured",
        "I Qtr-2023": "71",
        "II Qtr-2023": "63",
        "III Qtr-2023": "52",
        "IV Qtr-2023": "53",
        "Total 2023": "239",
        "%": "83"
    },
    {
        "Type of cases ": "RT+ve Treatment completed",
        "I Qtr-2023": "0",
        "II Qtr-2023": "1",
        "III Qtr-2023": "0",
        "IV Qtr-2023": "0",
        "Total 2023": "1",
        "%": "0"
    },
    {
        "Type of cases ": "RT +Ve Died",
        "I Qtr-2023": "3",
        "II Qtr-2023": "3",
        "III Qtr-2023": "1",
        "IV Qtr-2023": "1",
        "Total 2023": "8",
        "%": "3"
    },
    {
        "Type of cases ": "RT +ve Failure",
        "I Qtr-2023": "2",
        "II Qtr-2023": "1",
        "III Qtr-2023": "3",
        "IV Qtr-2023": "4",
        "Total 2023": "10",
        "%": "3"
    },
    {
        "Type of cases ": "RT +ve Lost to Follow-up",
        "I Qtr-2023": "3",
        "II Qtr-2023": "1",
        "III Qtr-2023": "1",
        "IV Qtr-2023": "2",
        "Total 2023": "7",
        "%": "2"
    },
    {
        "Type of cases ": "RT +ve Not Evaluated",
        "I Qtr-2023": "0",
        "II Qtr-2023": "0",
        "III Qtr-2023": "0",
        "IV Qtr-2023": "0",
        "Total 2023": "0",
        "%": "0.00"
    },
    {
        "Type of cases ": "RT +ve Treatment Regimen Changed",
        "I Qtr-2023": "12",
        "II Qtr-2023": "3",
        "III Qtr-2023": "4",
        "IV Qtr-2023": "4",
        "Total 2023": "23",
        "%": "7.99"
    },
    {
        "Type of cases ": "RT +ve Total",
        "I Qtr-2023": "91",
        "II Qtr-2023": "72",
        "III Qtr-2023": "61",
        "IV Qtr-2023": "64",
        "Total 2023": "288",
        "%": ""
    },
    {
        "Type of cases ": "RT Neg Cured",
        "I Qtr-2023": "",
        "II Qtr-2023": "",
        "III Qtr-2023": "",
        "IV Qtr-2023": "",
        "Total 2023": "0",
        "%": "0"
    },
    {
        "Type of cases ": "RT Neg Treatment completed",
        "I Qtr-2023": "59",
        "II Qtr-2023": "70",
        "III Qtr-2023": "68",
        "IV Qtr-2023": "79",
        "Total 2023": "276",
        "%": "97"
    },
    {
        "Type of cases ": "RT Neg Died",
        "I Qtr-2023": "1",
        "II Qtr-2023": "0",
        "III Qtr-2023": "3",
        "IV Qtr-2023": "0",
        "Total 2023": "4",
        "%": "1"
    },
    {
        "Type of cases ": "RT Neg Failure",
        "I Qtr-2023": "0",
        "II Qtr-2023": "0",
        "III Qtr-2023": "0",
        "IV Qtr-2023": "0",
        "Total 2023": "0",
        "%": "0"
    },
    {
        "Type of cases ": "RT Neg Lost to Follow-up",
        "I Qtr-2023": "1",
        "II Qtr-2023": "1",
        "III Qtr-2023": "1",
        "IV Qtr-2023": "1",
        "Total 2023": "4",
        "%": "1"
    },
    {
        "Type of cases ": "RT Neg Not Evaluated",
        "I Qtr-2023": "0",
        "II Qtr-2023": "0",
        "III Qtr-2023": "0",
        "IV Qtr-2023": "0",
        "Total 2023": "0",
        "%": "0.00"
    },
    {
        "Type of cases ": "RT Neg Treatment Regimen Changed",
        "I Qtr-2023": "1",
        "II Qtr-2023": "0",
        "III Qtr-2023": "0",
        "IV Qtr-2023": "0",
        "Total 2023": "1",
        "%": "0.35"
    },
    {
        "Type of cases ": "RT Neg Total",
        "I Qtr-2023": "62",
        "II Qtr-2023": "71",
        "III Qtr-2023": "72",
        "IV Qtr-2023": "80",
        "Total 2023": "285",
        "%": ""
    }
]