[
    {
        "Annexure M Contents": "TB Suspect examined Diagnosis ",
        "I Qtr-2015": "69",
        "II Qtr -2015": "32",
        "III Qtr-2015": "55",
        "IV Qtr- 2015": "43",
        "Total 2015": "199"
    },
    {
        "Annexure M Contents": "TB suspect found Positive",
        "I Qtr-2015": "2",
        "II Qtr -2015": "1",
        "III Qtr-2015": "2",
        "IV Qtr- 2015": "2",
        "Total 2015": "7"
    },
    {
        "Annexure M Contents": "TB suspect Repeat Sputum Examination",
        "I Qtr-2015": "0",
        "II Qtr -2015": "0",
        "III Qtr-2015": "0",
        "IV Qtr- 2015": "0",
        "Total 2015": "0"
    },
    {
        "Annexure M Contents": "TB suspect Found Positive & Repeat Examination ",
        "I Qtr-2015": "0",
        "II Qtr -2015": "0",
        "III Qtr-2015": "0",
        "IV Qtr- 2015": "0",
        "Total 2015": "0"
    },
    {
        "Annexure M Contents": "Follow up  Examination ",
        "I Qtr-2015": "4",
        "II Qtr -2015": "2",
        "III Qtr-2015": "0",
        "IV Qtr- 2015": "2",
        "Total 2015": "8"
    },
    {
        "Annexure M Contents": " Follow up positive ",
        "I Qtr-2015": "0",
        "II Qtr -2015": "0",
        "III Qtr-2015": "0",
        "IV Qtr- 2015": "0",
        "Total 2015": "0"
    },
    {
        "Annexure M Contents": "Total No.of slides",
        "I Qtr-2015": "129",
        "II Qtr -2015": "45",
        "III Qtr-2015": "103",
        "IV Qtr- 2015": "90",
        "Total 2015": "367"
    },
    {
        "Annexure M Contents": "Total No. of Positive Slides",
        "I Qtr-2015": "4",
        "II Qtr -2015": "2",
        "III Qtr-2015": "4",
        "IV Qtr- 2015": "4",
        "Total 2015": "14"
    },
    {
        "Annexure M Contents": "Total No. of Neg slides",
        "I Qtr-2015": "125",
        "II Qtr -2015": "43",
        "III Qtr-2015": "99",
        "IV Qtr- 2015": "86",
        "Total 2015": "353"
    },
    {
        "Annexure M Contents": "New adult OPD",
        "I Qtr-2015": "1283",
        "II Qtr -2015": "149",
        "III Qtr-2015": "263",
        "IV Qtr- 2015": "499",
        "Total 2015": "2194"
    }
]