[
    {
        "Annexure M Contents": "TB Suspect examined Diagnosis",
        "I Qtr-2016": "4436",
        "II Qtr -2016": "3376",
        "III Qtr-2016": "3566",
        "IV Qtr- 2016": "3344",
        "Total 2016": "14722"
    },
    {
        "Annexure M Contents": "TB suspect found Positive",
        "I Qtr-2016": "539",
        "II Qtr -2016": "514",
        "III Qtr-2016": "448",
        "IV Qtr- 2016": "424",
        "Total 2016": "1925"
    },
    {
        "Annexure M Contents": "TB suspect Repeat Sputum Examination",
        "I Qtr-2016": "79",
        "II Qtr -2016": "62",
        "III Qtr-2016": "47",
        "IV Qtr- 2016": "42",
        "Total 2016": "230"
    },
    {
        "Annexure M Contents": "TB suspect Found Positive & Repeat Examination",
        "I Qtr-2016": "5",
        "II Qtr -2016": "8",
        "III Qtr-2016": "4",
        "IV Qtr- 2016": "7",
        "Total 2016": "24"
    },
    {
        "Annexure M Contents": "Follow up Examination",
        "I Qtr-2016": "1316",
        "II Qtr -2016": "1240",
        "III Qtr-2016": "1127",
        "IV Qtr- 2016": "1207",
        "Total 2016": "4890"
    },
    {
        "Annexure M Contents": "Follow up positive",
        "I Qtr-2016": "108",
        "II Qtr -2016": "110",
        "III Qtr-2016": "79",
        "IV Qtr- 2016": "85",
        "Total 2016": "382"
    },
    {
        "Annexure M Contents": "Total No.of slides",
        "I Qtr-2016": "10953",
        "II Qtr -2016": "8543",
        "III Qtr-2016": "8607",
        "IV Qtr- 2016": "8265",
        "Total 2016": "36368"
    },
    {
        "Annexure M Contents": "Total No. of Positive Slides",
        "I Qtr-2016": "1187",
        "II Qtr -2016": "1137",
        "III Qtr-2016": "1015",
        "IV Qtr- 2016": "921",
        "Total 2016": "4260"
    },
    {
        "Annexure M Contents": "Total No. of Neg slides",
        "I Qtr-2016": "9352",
        "II Qtr -2016": "7416",
        "III Qtr-2016": "7592",
        "IV Qtr- 2016": "7340",
        "Total 2016": "31700"
    },
    {
        "Annexure M Contents": "New adult OPD",
        "I Qtr-2016": "72464",
        "II Qtr -2016": "42410",
        "III Qtr-2016": "74997",
        "IV Qtr- 2016": "66606",
        "Total 2016": "256477"
    }
]