[
    {
        "S.NO": "1",
        "Contents": "Total OPD Treated",
        "I Qtr-2022": "851",
        "II Qtr-2022": "773",
        "III Qtr-2022": "828",
        "IV Qtr-2022": "1013",
        "Annual 2022": "3465"
    },
    {
        "S.NO": "1.a",
        "Contents": "Skin OPD Treated",
        "I Qtr-2022": "657",
        "II Qtr-2022": "569",
        "III Qtr-2022": "618",
        "IV Qtr-2022": "809",
        "Annual 2022": "2653"
    },
    {
        "S.NO": "1.b",
        "Contents": "Respiratory OPD Treated",
        "I Qtr-2022": "192",
        "II Qtr-2022": "202",
        "III Qtr-2022": "206",
        "IV Qtr-2022": "201",
        "Annual 2022": "801"
    },
    {
        "S.NO": "1.c",
        "Contents": "Other OPD Treated",
        "I Qtr-2022": "2",
        "II Qtr-2022": "2",
        "III Qtr-2022": "4",
        "IV Qtr-2022": "3",
        "Annual 2022": "11"
    },
    {
        "S.NO": "2",
        "Contents": "Adult New PB Cases",
        "I Qtr-2022": "3",
        "II Qtr-2022": "0",
        "III Qtr-2022": "2",
        "IV Qtr-2022": "0",
        "Annual 2022": "5"
    },
    {
        "S.NO": "2.a",
        "Contents": "Adult New MB Cases",
        "I Qtr-2022": "4",
        "II Qtr-2022": "4",
        "III Qtr-2022": "3",
        "IV Qtr-2022": "1",
        "Annual 2022": "12"
    },
    {
        "S.NO": "2.b",
        "Contents": "Total Adult Cases",
        "I Qtr-2022": "7",
        "II Qtr-2022": "4",
        "III Qtr-2022": "5",
        "IV Qtr-2022": "1",
        "Annual 2022": "17"
    },
    {
        "S.NO": "2.c",
        "Contents": "Child New PB Cases",
        "I Qtr-2022": "0",
        "II Qtr-2022": "0",
        "III Qtr-2022": "0",
        "IV Qtr-2022": "0",
        "Annual 2022": "0"
    },
    {
        "S.NO": "2.d",
        "Contents": "Child New MB Cases",
        "I Qtr-2022": "0",
        "II Qtr-2022": "0",
        "III Qtr-2022": "0",
        "IV Qtr-2022": "0",
        "Annual 2022": "0"
    },
    {
        "S.NO": "2.e",
        "Contents": "Total Child Cases",
        "I Qtr-2022": "0",
        "II Qtr-2022": "0",
        "III Qtr-2022": "0",
        "IV Qtr-2022": "0",
        "Annual 2022": "0"
    },
    {
        "S.NO": "2.f",
        "Contents": "Total New Leprosy Cases detected",
        "I Qtr-2022": "7",
        "II Qtr-2022": "4",
        "III Qtr-2022": "5",
        "IV Qtr-2022": "1",
        "Annual 2022": "17"
    },
    {
        "S.NO": "2.g",
        "Contents": "Total Relapse Cases",
        "I Qtr-2022": "0",
        "II Qtr-2022": "0",
        "III Qtr-2022": "0",
        "IV Qtr-2022": "0",
        "Annual 2022": "0"
    },
    {
        "S.NO": "2.h",
        "Contents": "Female New PB Cases",
        "I Qtr-2022": "1",
        "II Qtr-2022": "0",
        "III Qtr-2022": "1",
        "IV Qtr-2022": "0",
        "Annual 2022": "2"
    },
    {
        "S.NO": "2.i",
        "Contents": "Female New MB Cases",
        "I Qtr-2022": "0",
        "II Qtr-2022": "1",
        "III Qtr-2022": "0",
        "IV Qtr-2022": "0",
        "Annual 2022": "1"
    },
    {
        "S.NO": "2.j",
        "Contents": "Total Female Cases",
        "I Qtr-2022": "1",
        "II Qtr-2022": "1",
        "III Qtr-2022": "1",
        "IV Qtr-2022": "0",
        "Annual 2022": "3"
    },
    {
        "S.NO": "2.k",
        "Contents": "Adult New PB G-I-D Cases",
        "I Qtr-2022": "0",
        "II Qtr-2022": "0",
        "III Qtr-2022": "0",
        "IV Qtr-2022": "0",
        "Annual 2022": "0"
    },
    {
        "S.NO": "2.l",
        "Contents": "Adult New MB G-I-D Cases",
        "I Qtr-2022": "2",
        "II Qtr-2022": "2",
        "III Qtr-2022": "0",
        "IV Qtr-2022": "0",
        "Annual 2022": "4"
    },
    {
        "S.NO": "2.m",
        "Contents": "Total Adult G-I-D Cases",
        "I Qtr-2022": "2",
        "II Qtr-2022": "2",
        "III Qtr-2022": "0",
        "IV Qtr-2022": "0",
        "Annual 2022": "4"
    },
    {
        "S.NO": "2.n",
        "Contents": "Adult New PB G-II-D Cases",
        "I Qtr-2022": "0",
        "II Qtr-2022": "0",
        "III Qtr-2022": "1",
        "IV Qtr-2022": "0",
        "Annual 2022": "1"
    },
    {
        "S.NO": "2.o",
        "Contents": "Adult New MB G-II-D Cases",
        "I Qtr-2022": "1",
        "II Qtr-2022": "2",
        "III Qtr-2022": "3",
        "IV Qtr-2022": "0",
        "Annual 2022": "6"
    },
    {
        "S.NO": "2.p",
        "Contents": "Total Adult G-II-D Cases",
        "I Qtr-2022": "1",
        "II Qtr-2022": "2",
        "III Qtr-2022": "4",
        "IV Qtr-2022": "0",
        "Annual 2022": "7"
    },
    {
        "S.NO": "2.q",
        "Contents": "Child New PB G-I-D Cases",
        "I Qtr-2022": "0",
        "II Qtr-2022": "0",
        "III Qtr-2022": "0",
        "IV Qtr-2022": "0",
        "Annual 2022": "0"
    },
    {
        "S.NO": "2.r",
        "Contents": "Child New MB G-I-D Cases",
        "I Qtr-2022": "0",
        "II Qtr-2022": "0",
        "III Qtr-2022": "0",
        "IV Qtr-2022": "0",
        "Annual 2022": "0"
    },
    {
        "S.NO": "2.s",
        "Contents": "Total Child G-I-D Cases",
        "I Qtr-2022": "0",
        "II Qtr-2022": "0",
        "III Qtr-2022": "0",
        "IV Qtr-2022": "0",
        "Annual 2022": "0"
    },
    {
        "S.NO": "2.t",
        "Contents": "Child New PB G-II-D Cases",
        "I Qtr-2022": "0",
        "II Qtr-2022": "0",
        "III Qtr-2022": "0",
        "IV Qtr-2022": "0",
        "Annual 2022": "0"
    },
    {
        "S.NO": "2.u",
        "Contents": "Child New MB G-II-D Cases",
        "I Qtr-2022": "0",
        "II Qtr-2022": "0",
        "III Qtr-2022": "0",
        "IV Qtr-2022": "0",
        "Annual 2022": "0"
    },
    {
        "S.NO": "2.v",
        "Contents": "Total Child G-II-D Cases",
        "I Qtr-2022": "0",
        "II Qtr-2022": "0",
        "III Qtr-2022": "0",
        "IV Qtr-2022": "0",
        "Annual 2022": "0"
    },
    {
        "S.NO": "3",
        "Contents": "Type-1 Lepra Reaction Male Cases",
        "I Qtr-2022": "6",
        "II Qtr-2022": "4",
        "III Qtr-2022": "4",
        "IV Qtr-2022": "4",
        "Annual 2022": "18"
    },
    {
        "S.NO": "3.a",
        "Contents": "Type-1 Lepra Reaction Female Cases",
        "I Qtr-2022": "1",
        "II Qtr-2022": "2",
        "III Qtr-2022": "1",
        "IV Qtr-2022": "2",
        "Annual 2022": "6"
    },
    {
        "S.NO": "3.b",
        "Contents": "Total Type-1 Lepra Reaction Cases",
        "I Qtr-2022": "7",
        "II Qtr-2022": "6",
        "III Qtr-2022": "5",
        "IV Qtr-2022": "6",
        "Annual 2022": "24"
    },
    {
        "S.NO": "3.c",
        "Contents": "Type-2 Lepra Reaction Male Cases",
        "I Qtr-2022": "1",
        "II Qtr-2022": "3",
        "III Qtr-2022": "1",
        "IV Qtr-2022": "0",
        "Annual 2022": "5"
    },
    {
        "S.NO": "3.d",
        "Contents": "Type-2 Lepra Reaction Female Cases",
        "I Qtr-2022": "2",
        "II Qtr-2022": "0",
        "III Qtr-2022": "1",
        "IV Qtr-2022": "0",
        "Annual 2022": "3"
    },
    {
        "S.NO": "3.e",
        "Contents": "Total Type-2 Lepra Reaction Cases",
        "I Qtr-2022": "3",
        "II Qtr-2022": "3",
        "III Qtr-2022": "2",
        "IV Qtr-2022": "0",
        "Annual 2022": "8"
    },
    {
        "S.NO": "4",
        "Contents": "Total MCR Footwear Provided",
        "I Qtr-2022": "29",
        "II Qtr-2022": "34",
        "III Qtr-2022": "45",
        "IV Qtr-2022": "22",
        "Annual 2022": "130"
    },
    {
        "S.NO": "5",
        "Contents": "Male Cases RCS Done",
        "I Qtr-2022": "0",
        "II Qtr-2022": "9",
        "III Qtr-2022": "9",
        "IV Qtr-2022": "8",
        "Annual 2022": "26"
    },
    {
        "S.NO": "5.a",
        "Contents": "Female Cases RCS Done",
        "I Qtr-2022": "0",
        "II Qtr-2022": "2",
        "III Qtr-2022": "2",
        "IV Qtr-2022": "0",
        "Annual 2022": "4"
    },
    {
        "S.NO": "5.b",
        "Contents": "Major RCS Done ",
        "I Qtr-2022": "0",
        "II Qtr-2022": "11",
        "III Qtr-2022": "11",
        "IV Qtr-2022": "8",
        "Annual 2022": "30"
    },
    {
        "S.NO": "5.c",
        "Contents": "Eye Male RCS Done",
        "I Qtr-2022": "0",
        "II Qtr-2022": "2",
        "III Qtr-2022": "2",
        "IV Qtr-2022": "1",
        "Annual 2022": "5"
    },
    {
        "S.NO": "5.d",
        "Contents": "Eye Female RCS Done",
        "I Qtr-2022": "0",
        "II Qtr-2022": "0",
        "III Qtr-2022": "0",
        "IV Qtr-2022": "0",
        "Annual 2022": "0"
    },
    {
        "S.NO": "5.e",
        "Contents": "Total Eye RCS Done",
        "I Qtr-2022": "0",
        "II Qtr-2022": "2",
        "III Qtr-2022": "2",
        "IV Qtr-2022": "1",
        "Annual 2022": "5"
    },
    {
        "S.NO": "5.f",
        "Contents": "Hand Male RCS Done",
        "I Qtr-2022": "0",
        "II Qtr-2022": "4",
        "III Qtr-2022": "4",
        "IV Qtr-2022": "3",
        "Annual 2022": "11"
    },
    {
        "S.NO": "5.g",
        "Contents": "Hand Female RCS Done",
        "I Qtr-2022": "0",
        "II Qtr-2022": "2",
        "III Qtr-2022": "2",
        "IV Qtr-2022": "0",
        "Annual 2022": "4"
    },
    {
        "S.NO": "5.h",
        "Contents": "Total Hand RCS Done",
        "I Qtr-2022": "0",
        "II Qtr-2022": "6",
        "III Qtr-2022": "6",
        "IV Qtr-2022": "3",
        "Annual 2022": "15"
    },
    {
        "S.NO": "5.i",
        "Contents": "Foot Male RCS Done",
        "I Qtr-2022": "0",
        "II Qtr-2022": "3",
        "III Qtr-2022": "3",
        "IV Qtr-2022": "4",
        "Annual 2022": "10"
    },
    {
        "S.NO": "5.j",
        "Contents": "Foot Female RCS Done",
        "I Qtr-2022": "0",
        "II Qtr-2022": "0",
        "III Qtr-2022": "0",
        "IV Qtr-2022": "0",
        "Annual 2022": "0"
    },
    {
        "S.NO": "5.k",
        "Contents": "Total Foot RCS Done",
        "I Qtr-2022": "0",
        "II Qtr-2022": "3",
        "III Qtr-2022": "3",
        "IV Qtr-2022": "4",
        "Annual 2022": "10"
    },
    {
        "S.NO": "6",
        "Contents": "Male Minor Surgeries Done",
        "I Qtr-2022": "8",
        "II Qtr-2022": "9",
        "III Qtr-2022": "6",
        "IV Qtr-2022": "10",
        "Annual 2022": "33"
    },
    {
        "S.NO": "6.a",
        "Contents": "Female Minor Surgeries Done",
        "I Qtr-2022": "3",
        "II Qtr-2022": "1",
        "III Qtr-2022": "2",
        "IV Qtr-2022": "1",
        "Annual 2022": "7"
    },
    {
        "S.NO": "6.b",
        "Contents": "Total Minor Surgeries Done",
        "I Qtr-2022": "11",
        "II Qtr-2022": "10",
        "III Qtr-2022": "8",
        "IV Qtr-2022": "11",
        "Annual 2022": "40"
    },
    {
        "S.NO": "7",
        "Contents": "LEP-House Support for Male Cases",
        "I Qtr-2022": "0",
        "II Qtr-2022": "0",
        "III Qtr-2022": "0",
        "IV Qtr-2022": "0",
        "Annual 2022": "0"
    },
    {
        "S.NO": "7.a",
        "Contents": "LEP-House Support for Female Cases",
        "I Qtr-2022": "0",
        "II Qtr-2022": "0",
        "III Qtr-2022": "0",
        "IV Qtr-2022": "0",
        "Annual 2022": "0"
    },
    {
        "S.NO": "7.b",
        "Contents": "Total LEP-House Supported",
        "I Qtr-2022": "0",
        "II Qtr-2022": "0",
        "III Qtr-2022": "0",
        "IV Qtr-2022": "0",
        "Annual 2022": "0"
    },
    {
        "S.NO": "7.c",
        "Contents": "Socio-Economic Support for Male Cases",
        "I Qtr-2022": "0",
        "II Qtr-2022": "0",
        "III Qtr-2022": "0",
        "IV Qtr-2022": "0",
        "Annual 2022": "0"
    },
    {
        "S.NO": "7.d",
        "Contents": "Socio-Economic Support for Female Cases",
        "I Qtr-2022": "0",
        "II Qtr-2022": "0",
        "III Qtr-2022": "0",
        "IV Qtr-2022": "0",
        "Annual 2022": "0"
    },
    {
        "S.NO": "7.e",
        "Contents": "LEP, Socio-Economic Supported",
        "I Qtr-2022": "0",
        "II Qtr-2022": "0",
        "III Qtr-2022": "0",
        "IV Qtr-2022": "0",
        "Annual 2022": "0"
    },
    {
        "S.NO": "7.f",
        "Contents": "Education Support for Male cases",
        "I Qtr-2022": "0",
        "II Qtr-2022": "0",
        "III Qtr-2022": "0",
        "IV Qtr-2022": "0",
        "Annual 2022": "0"
    },
    {
        "S.NO": "7.g",
        "Contents": "Education Support for Female cases",
        "I Qtr-2022": "0",
        "II Qtr-2022": "0",
        "III Qtr-2022": "0",
        "IV Qtr-2022": "0",
        "Annual 2022": "0"
    },
    {
        "S.NO": "7.h",
        "Contents": "Total Education Supported",
        "I Qtr-2022": "0",
        "II Qtr-2022": "0",
        "III Qtr-2022": "0",
        "IV Qtr-2022": "0",
        "Annual 2022": "0"
    },
    {
        "S.NO": "8",
        "Contents": "Total Beds Available for Leprosy",
        "I Qtr-2022": "75",
        "II Qtr-2022": "75",
        "III Qtr-2022": "75",
        "IV Qtr-2022": "75",
        "Annual 2022": "75"
    },
    {
        "S.NO": "8.a",
        "Contents": "Total Leprosy cases Admitted",
        "I Qtr-2022": "174",
        "II Qtr-2022": "183",
        "III Qtr-2022": "172",
        "IV Qtr-2022": "144",
        "Annual 2022": "673"
    },
    {
        "S.NO": "8.b",
        "Contents": "Lepra Reaction In-Patients Managed",
        "I Qtr-2022": "3",
        "II Qtr-2022": "2",
        "III Qtr-2022": "5",
        "IV Qtr-2022": "2",
        "Annual 2022": "12"
    },
    {
        "S.NO": "8.c",
        "Contents": "RCS In-Patients Managed",
        "I Qtr-2022": "13",
        "II Qtr-2022": "24",
        "III Qtr-2022": "36",
        "IV Qtr-2022": "20",
        "Annual 2022": "93"
    },
    {
        "S.NO": "8.d",
        "Contents": "Planter Ulcers In-Patients Managed",
        "I Qtr-2022": "158",
        "II Qtr-2022": "157",
        "III Qtr-2022": "131",
        "IV Qtr-2022": "122",
        "Annual 2022": "568"
    },
    {
        "S.NO": "8.e",
        "Contents": "Total Beddays for Leprosy Cases",
        "I Qtr-2022": "3217",
        "II Qtr-2022": "3590",
        "III Qtr-2022": "3388",
        "IV Qtr-2022": "2838",
        "Annual 2022": "13033"
    },
    {
        "S.NO": "8.f",
        "Contents": "Bed Occupancy Rate for Leprosy Cases",
        "I Qtr-2022": "47.7",
        "II Qtr-2022": "53.2",
        "III Qtr-2022": "50.2",
        "IV Qtr-2022": "42.0",
        "Annual 2022": "48.2"
    },
    {
        "S.NO": "9",
        "Contents": "Total Beds Available for TB cases",
        "I Qtr-2022": "5",
        "II Qtr-2022": "5",
        "III Qtr-2022": "5",
        "IV Qtr-2022": "5",
        "Annual 2022": "5"
    },
    {
        "S.NO": "9.a",
        "Contents": "Total DS TB In- Patients Managed",
        "I Qtr-2022": "0",
        "II Qtr-2022": "0",
        "III Qtr-2022": "0",
        "IV Qtr-2022": "0",
        "Annual 2022": "0"
    },
    {
        "S.NO": "9.b",
        "Contents": "Total DR TB   In-Patients Managed",
        "I Qtr-2022": "0",
        "II Qtr-2022": "0",
        "III Qtr-2022": "0",
        "IV Qtr-2022": "0",
        "Annual 2022": "0"
    },
    {
        "S.NO": "9.c",
        "Contents": "Total Beddays for TB Cases ",
        "I Qtr-2022": "0",
        "II Qtr-2022": "0",
        "III Qtr-2022": "0",
        "IV Qtr-2022": "0",
        "Annual 2022": "0"
    },
    {
        "S.NO": "9.d",
        "Contents": "Bed Occupancy Rate for TB Cases",
        "I Qtr-2022": "0.0",
        "II Qtr-2022": "0.0",
        "III Qtr-2022": "0.0",
        "IV Qtr-2022": "0.0",
        "Annual 2022": "0"
    }
]